ansictrls/__init__.py
ansictrls/ctrls.py
ansictrls/sgr.py
ansictrls/spec.py
ansictrls-0.3.0.dist-info/LICENSE.txt
ansictrls-0.3.0.dist-info/METADATA
ansictrls-0.3.0.dist-info/WHEEL
ansictrls-0.3.0.dist-info/top_level.txt
ansictrls-0.3.0.dist-info/RECORD
